backend.v
module backend(
    input i_resetbAll,
    input i_clk,
    input i_sclk,
    input i_sdin,
    input i_clk_vco1,
    input i_clk_vco2,
    output reg o_ready,
    output reg o_vco1_fast,
    output reg o_resetb1,
    output reg [2:0] o_gainA1,
    output reg o_resetb2,
    output reg [1:0] o_gainA2,
    output reg o_resetbvco1,
    output reg o_resetbvco2
);

reg [4:0] counter1;
reg [7:0] vco1_counter;
reg [7:0] vco2_counter;
reg [4:0] startup_state;
reg [4:0] shift_register;
reg data_received;
reg prev_isclk;

always @(posedge i_clk or negedge i_resetbAll) begin
    if (!i_resetbAll) begin
        // Reset the entire backend
        counter1 <= 0;
        vco1_counter <= 0;
        vco2_counter <=0;
        startup_state <= 0;
        shift_register <= 0;
        data_received <= 0;
        o_resetb1 <= 1'b0;
        o_resetb2 <= 1'b0;
        o_gainA1 <= 3'b000;
        o_gainA2 <= 2'b00;
        o_resetbvco1 <= 1'b0;
        o_resetbvco2 <= 1'b0;
        o_ready <= 1'b0;
        o_vco1_fast <= 1'b1;
        prev_isclk <= 1'b1;
    end else begin
        // State machine for the startup sequence
        case(startup_state)
            0: begin
                if (counter1 < 5) begin
                    if(i_sclk&&!prev_isclk)begin
                        shift_register[4-counter1] <=i_sdin;
                        counter1 <= counter1 +1;
                    end
                end else begin
                    counter1 <= 0;
                    o_gainA2 <= shift_register[1:0];
                    o_gainA1 <= shift_register[4:2];
                    startup_state <= 1;
                end
                prev_isclk <= i_sclk;
            end
            1: begin
                // Wait for five clock cycles
                if (counter1 < 4) begin
                    counter1 <= counter1 + 1;
                end else begin
                    counter1 <= 0;
                    startup_state <= 2;
                end
            end
            2: begin
                // Set o_resetbvco1 and o_resetbvco2
                o_resetbvco1 <= 1'b1;
                o_resetbvco2 <= 1'b1;
                startup_state <= 3;
            end
            3: begin
                // Wait for 20 clock cycles
                if (counter1 < 20) begin
                    counter1 <= counter1 + 1;
                end else begin
                    counter1 <= 0;
                    startup_state <= 4;
                end
            end
            4: begin
                // Set o_resetb1 and o_resetb2
                o_resetb1 <= 1'b1;
                o_resetb2 <= 1'b1;
                startup_state <= 5;
            end
            5: begin
                // Wait for 10 clock cycles
                if (counter1 < 10) begin
                    counter1 <= counter1 + 1;
                end else begin
                    startup_state <= 6;
                    counter1 <= 0;
                end
            end
            6: begin

                if (vco1_counter >= vco2_counter)begin
                    o_vco1_fast <= 1'b1;
                end
                
                // Set o_ready
                o_ready <= 1'b1;
                startup_state <= 7;
                
            end
            default: begin
                // No more actions required, hold values
            end
        endcase

        
    end
end

always @(posedge i_clk_vco1)begin
    if (startup_state < 6)begin
        vco1_counter <= vco1_counter + 1;
    end
    else begin
        vco1_counter <= 0;
    end
end

always @(posedge i_clk_vco2)begin
    if (startup_state < 6)begin
        vco2_counter <= vco2_counter + 1;
    end
    else begin
        vco2_counter <= 0;
    end
end

endmodule

FPGA_model.v
///////////////////////////////////////////////////////////////////////////////
/*FPGA model
 * Generates reset signal for the chip
 * Sends out progamming bits to the chip
*/
module FPGA_model(	i_resetbFPGA,
			i_ready,
			i_mainclk,
			i_vco1_fast,
			o_resetbAll,
			o_sclk, 
			o_sdout);

//============================================================================
//Parameter declarations
parameter opcode_gainA1	= 6; //range: 0-7. Gain for amplifier 1
parameter opcode_gainA2	= 1; //range: 0-3. Gain for amplifier 2

//FPGA states
parameter sRESET 	= 0; //Reset all internal variables. Make o_resetbAll=0.
parameter sPROGRAM	= 1; //Send programming bits to chip.
parameter sIDLE		= 2; //Do nothing.
//===========================================================================
//Input output declarations
input i_resetbFPGA; 		//resets FPGA
input i_ready;			//Alerts FPGA that chip is programmed and ready
input i_mainclk;		//Main clock
input i_vco1_fast;		//Goes high when vco1 is faster than vco2
output reg o_resetbAll;		//Reset for the chip
output reg o_sclk;		//Serial clock for communication
output reg o_sdout;		//Serial data out from FPGA (to chip)


//Internal wire, reg declarations
reg [1:0] FPGAstate;		//Holds the state of FPGA
reg [3:0] count;		//Used for controlling sclk generation and transmission of serial data
reg mainclkby2, mainclkby4, mainclkby8, mainclkby16; //Low frequency clocks derived from mainclk

//=============================================================
//BEHAVIORAL DESCRIPTION
//=============================================================
// Setting the FPGA state
always @ (posedge(i_mainclk) or negedge(i_resetbFPGA))
begin
	if(i_resetbFPGA == 0)
		FPGAstate <= sRESET;
	else
	begin
		case(FPGAstate)
		sRESET: FPGAstate <= sPROGRAM;
		sPROGRAM: 
		begin	
			if(count== 10)
				FPGAstate <= sIDLE;
			else
				FPGAstate <= sPROGRAM;
		end
		sIDLE: FPGAstate <=sIDLE;
		default: FPGAstate <= sIDLE;
		endcase
	end
end
//========================================================
/*resetbALL
 * resetbAll=0, when FPGA is reset. 
 * resetbAll=1 at all other times.
*/
always @(posedge(i_mainclk) or negedge(i_resetbFPGA))
begin
	if(i_resetbFPGA == 0)
		o_resetbAll <= 0;
	else
	begin
		if(FPGAstate == sRESET)
			o_resetbAll <= 0;
		else
			o_resetbAll <= 1;
	end
end
//==========================================================
/* Generation of low frequency clocks from mainclk using divide-by-2 method
*/
always @ (posedge(i_mainclk) or negedge(i_resetbFPGA))
begin
	if(i_resetbFPGA == 0)
		mainclkby2 <= 0;
	else
		mainclkby2 <= ~mainclkby2;
end

always @ (posedge(mainclkby2) or negedge(i_resetbFPGA))
begin
	if(i_resetbFPGA == 0)
		mainclkby4 <= 0;
	else
		mainclkby4 <= ~mainclkby4;
end

always @(posedge(mainclkby4) or negedge(i_resetbFPGA))
begin
	if(i_resetbFPGA == 0)
		mainclkby8 <= 0;
	else
		mainclkby8 <= ~mainclkby8;
end

always @(posedge(mainclkby8) or negedge(i_resetbFPGA))
begin
	if(i_resetbFPGA == 0)
		mainclkby16 <= 0;
	else
		mainclkby16 <= ~mainclkby16;
end
//==========================================================
/*count
 * used for the generation of sclk and selecting the data to be sent in through sdin
 */
always	@(posedge(mainclkby16) or negedge(i_resetbFPGA))
begin
	if(i_resetbFPGA == 0)
		count <= 0;
	else
	begin
		if(FPGAstate == sPROGRAM)
		begin
			if(count == 11)
				count <= count;
			else
				count <= count+1;
		end
		else
			count <= count;
	end
end
//=========================================================
/*sclk
 * sclk is a clock only when the FPGA is programming the chip.
 */
always @ (posedge(mainclkby16) or negedge(i_resetbFPGA))
begin
	if(i_resetbFPGA == 0)
		o_sclk <= 1;
	else
	begin
		if(FPGAstate == sPROGRAM)
		begin
			if (count >= 1 && count <= 10)
				o_sclk <= ~o_sclk;
			else
				o_sclk <= 1;
		end
		else
			o_sclk <= 1;
	end
end

//=========================================================
/*sdin
 *serial data out from FPGA
 */
always @ (negedge(o_sclk) or negedge(i_resetbFPGA))
begin
	if(i_resetbFPGA == 0)
		o_sdout <= 0;
	else
	begin
		if(FPGAstate == sPROGRAM)
		begin
			case(count)
			4'd2: o_sdout <= opcode_gainA1[2];
			4'd4: o_sdout <= opcode_gainA1[1];
			4'd6: o_sdout <= opcode_gainA1[0];
			4'd8: o_sdout <= opcode_gainA2[1];
			4'd10: o_sdout <= opcode_gainA2[0];
			default: o_sdout <= o_sdout;
			endcase
		end
		else
			o_sdout <= 0;
		
	end
end
//==========================================================
endmodule

backend_tb.v
// Testbanch module for the backend. This is has a module instantiation for
// the FPGA_model and the backend.
`timescale 1ns / 100ps
//==========================================================================
//Change the Verilog filenames approppriately.
`include "FPGA_model.v"
`include "backend.v"
//=========================================================================

module backend_tb();

reg resetbFPGA;
reg main_clk;
reg vco1_clockmodel, vco2_clockmodel; 

wire [2:0]gainA1 ; 
wire [1:0]gainA2 ;
wire resetbAll, resetb1, resetb2, resetbvco1, resetbvco2; 
wire vco1_clk, vco2_clk;
wire sclk, sdin;
wire ready;
wire vco1_fast;


//==========================================================================
//FPGA model instantiation
FPGA_model   FPGA_obj(	.i_resetbFPGA (resetbFPGA),
			.i_ready (ready),
			.o_resetbAll (resetbAll),
			.i_mainclk (main_clk),
			.o_sclk (sclk), 
			.o_sdout (sdin),
			.i_vco1_fast (vco1_fast) );

// Backend instantiation 
backend backend_obj (	.i_resetbAll (resetbAll),
			.i_clk (main_clk),
			.i_sclk (sclk),
			.i_sdin (sdin),
			.i_clk_vco1 (vco1_clk),
			.i_clk_vco2 (vco2_clk),
			.o_ready (ready),
                        .o_vco1_fast (vco1_fast),
			.o_resetb1 (resetb1),
			.o_gainA1 (gainA1),
			.o_resetb2 (resetb2),
			.o_gainA2 (gainA2),
			.o_resetbvco1 (resetbvco1),
			.o_resetbvco2 (resetbvco2)
			);
//============================================================================
// VCO clock model
assign vco1_clk = (resetbvco1)?vco1_clockmodel:0;
assign vco2_clk = (resetbvco2)?vco2_clockmodel:0;

//============================================================================

//Test signal generation
initial
begin
	$dumpfile("backend_tb.vcd"); // Specify the VCD file name
    $dumpvars(0, backend_tb);  
	resetbFPGA <= 0;
	main_clk <= 0;
	vco1_clockmodel <= 0;
	vco2_clockmodel <= 0;

	#4 resetbFPGA <= 1;
	
	// Define the number of simulation cycles
    // integer num_cycles = 1000; // Adjust as needed

    // for (integer sim_time = 0; sim_time < 1000; sim_time = sim_time + 1) begin
    //     // Periodically print the values of gainA1 and gainA2
    //     begin
    //         $display("sim_time = %d, gainA1 = %b, gainA2 = %b, sdin = %b", sim_time, gainA1, gainA2, sdin);
    //     end

    //     // Add other conditions to set stop_simulation if needed
    //     // For example: if (resetbAll == 0) stop_simulation = 1;

    //     // Delay for 1 time unit
    //     #1;
    // end
	#1500;
    // Terminate the simulation
    $finish;
	
end

//Generation of main_clk 
always #2.5 main_clk <= ~main_clk;

//Generation of internal clock models for the VCOs
always #1 vco1_clockmodel <= ~vco1_clockmodel;
always #2 vco2_clockmodel <= ~vco2_clockmodel;


//============================================================================
endmodule

backend_tb.vcd
$date
	Fri Oct 27 06:56:43 2023
$end
$version
	Icarus Verilog
$end
$timescale
	100ps
$end
$scope module backend_tb $end
$var wire 1 ! vco2_clk $end
$var wire 1 " vco1_fast $end
$var wire 1 # vco1_clk $end
$var wire 1 $ sdin $end
$var wire 1 % sclk $end
$var wire 1 & resetbvco2 $end
$var wire 1 ' resetbvco1 $end
$var wire 1 ( resetbAll $end
$var wire 1 ) resetb2 $end
$var wire 1 * resetb1 $end
$var wire 1 + ready $end
$var wire 2 , gainA2 [1:0] $end
$var wire 3 - gainA1 [2:0] $end
$var reg 1 . main_clk $end
$var reg 1 / resetbFPGA $end
$var reg 1 0 vco1_clockmodel $end
$var reg 1 1 vco2_clockmodel $end
$scope module FPGA_obj $end
$var wire 1 . i_mainclk $end
$var wire 1 / i_resetbFPGA $end
$var wire 1 " i_vco1_fast $end
$var wire 1 + i_ready $end
$var parameter 32 2 opcode_gainA1 $end
$var parameter 32 3 opcode_gainA2 $end
$var parameter 32 4 sIDLE $end
$var parameter 32 5 sPROGRAM $end
$var parameter 32 6 sRESET $end
$var reg 2 7 FPGAstate [1:0] $end
$var reg 4 8 count [3:0] $end
$var reg 1 9 mainclkby16 $end
$var reg 1 : mainclkby2 $end
$var reg 1 ; mainclkby4 $end
$var reg 1 < mainclkby8 $end
$var reg 1 ( o_resetbAll $end
$var reg 1 % o_sclk $end
$var reg 1 $ o_sdout $end
$upscope $end
$scope module backend_obj $end
$var wire 1 . i_clk $end
$var wire 1 # i_clk_vco1 $end
$var wire 1 ! i_clk_vco2 $end
$var wire 1 ( i_resetbAll $end
$var wire 1 % i_sclk $end
$var wire 1 $ i_sdin $end
$var reg 5 = counter1 [4:0] $end
$var reg 1 > data_received $end
$var reg 3 ? o_gainA1 [2:0] $end
$var reg 2 @ o_gainA2 [1:0] $end
$var reg 1 + o_ready $end
$var reg 1 * o_resetb1 $end
$var reg 1 ) o_resetb2 $end
$var reg 1 ' o_resetbvco1 $end
$var reg 1 & o_resetbvco2 $end
$var reg 1 " o_vco1_fast $end
$var reg 1 A prev_isclk $end
$var reg 5 B shift_register [4:0] $end
$var reg 5 C startup_state [4:0] $end
$var reg 8 D vco1_counter [7:0] $end
$var reg 8 E vco2_counter [7:0] $end
$upscope $end
$upscope $end
$enddefinitions $end
$comment Show the parameter values. $end
$dumpall
b0 6
b1 5
b10 4
b1 3
b110 2
$end
#0
$dumpvars
b0 E
b0 D
b0 C
b0 B
1A
b0 @
b0 ?
0>
b0 =
0<
0;
0:
09
b0 8
b0 7
01
00
0/
0.
b0 -
b0 ,
0+
0*
0)
0(
0'
0&
1%
0$
0#
1"
0!
$end
#10
10
#20
00
11
#25
1.
#30
10
#40
00
01
1/
#50
10
0.
#60
00
11
#70
10
#75
b1 8
19
1<
1;
b1 7
1:
1.
#80
00
01
#90
10
#100
00
11
0.
#110
10
#120
00
01
#125
0:
1(
1.
#130
10
#140
00
11
#150
10
0.
#160
00
01
#170
10
#175
0;
1:
1.
#180
00
11
#190
10
#200
00
01
0.
#210
10
#220
00
11
#225
0:
1.
#230
10
#240
00
01
#250
10
0.
#260
00
11
#270
10
#275
0<
1;
1:
1.
#280
00
01
#290
10
#300
00
11
0.
#310
10
#320
00
01
#325
0:
1.
#330
10
#340
00
11
#350
10
0.
#360
00
01
#370
10
#375
0;
1:
1.
#380
00
11
#390
10
#400
00
01
0.
#410
10
#420
00
11
#425
0:
1.
#430
10
#440
00
01
#450
10
0.
#460
00
11
#470
10
#475
09
1<
1;
1:
1.
#480
00
01
#490
10
#500
00
11
0.
#510
10
#520
00
01
#525
0:
1.
#530
10
#540
00
11
#550
10
0.
#560
00
01
#570
10
#575
0;
1:
1.
#580
00
11
#590
10
#600
00
01
0.
#610
10
#620
00
11
#625
0:
1.
#630
10
#640
00
01
#650
10
0.
#660
00
11
#670
10
#675
0<
1;
1:
1.
#680
00
01
#690
10
#700
00
11
0.
#710
10
#720
00
01
#725
0:
1.
#730
10
#740
00
11
#750
10
0.
#760
00
01
#770
10
#775
0;
1:
1.
#780
00
11
#790
10
#800
00
01
0.
#810
10
#820
00
11
#825
0:
1.
#830
10
#840
00
01
#850
10
0.
#860
00
11
#870
10
#875
1$
b10 8
0%
19
1<
1;
1:
1.
#880
00
01
#890
10
#900
00
11
0.
#910
10
#920
00
01
#925
0:
0A
1.
#930
10
#940
00
11
#950
10
0.
#960
00
01
#970
10
#975
0;
1:
1.
#980
00
11
#990
10
#1000
00
01
0.
#1010
10
#1020
00
11
#1025
0:
1.
#1030
10
#1040
00
01
#1050
10
0.
#1060
00
11
#1070
10
#1075
0<
1;
1:
1.
#1080
00
01
#1090
10
#1100
00
11
0.
#1110
10
#1120
00
01
#1125
0:
1.
#1130
10
#1140
00
11
#1150
10
0.
#1160
00
01
#1170
10
#1175
0;
1:
1.
#1180
00
11
#1190
10
#1200
00
01
0.
#1210
10
#1220
00
11
#1225
0:
1.
#1230
10
#1240
00
01
#1250
10
0.
#1260
00
11
#1270
10
#1275
09
1<
1;
1:
1.
#1280
00
01
#1290
10
#1300
00
11
0.
#1310
10
#1320
00
01
#1325
0:
1.
#1330
10
#1340
00
11
#1350
10
0.
#1360
00
01
#1370
10
#1375
0;
1:
1.
#1380
00
11
#1390
10
#1400
00
01
0.
#1410
10
#1420
00
11
#1425
0:
1.
#1430
10
#1440
00
01
#1450
10
0.
#1460
00
11
#1470
10
#1475
0<
1;
1:
1.
#1480
00
01
#1490
10
#1500
00
11
0.
#1510
10
#1520
00
01
#1525
0:
1.
#1530
10
#1540
00
11
#1550
10
0.
#1560
00
01
#1570
10
#1575
0;
1:
1.
#1580
00
11
#1590
10
#1600
00
01
0.
#1610
10
#1620
00
11
#1625
0:
1.
#1630
10
#1640
00
01
#1650
10
0.
#1660
00
11
#1670
10
#1675
1%
b11 8
19
1<
1;
1:
1.
#1680
00
01
#1690
10
#1700
00
11
0.
#1710
10
#1720
00
01
#1725
0:
1A
b1 =
b10000 B
1.
#1730
10
#1740
00
11
#1750
10
0.
#1760
00
01
#1770
10
#1775
0;
1:
1.
#1780
00
11
#1790
10
#1800
00
01
0.
#1810
10
#1820
00
11
#1825
0:
1.
#1830
10
#1840
00
01
#1850
10
0.
#1860
00
11
#1870
10
#1875
0<
1;
1:
1.
#1880
00
01
#1890
10
#1900
00
11
0.
#1910
10
#1920
00
01
#1925
0:
1.
#1930
10
#1940
00
11
#1950
10
0.
#1960
00
01
#1970
10
#1975
0;
1:
1.
#1980
00
11
#1990
10
#2000
00
01
0.
#2010
10
#2020
00
11
#2025
0:
1.
#2030
10
#2040
00
01
#2050
10
0.
#2060
00
11
#2070
10
#2075
09
1<
1;
1:
1.
#2080
00
01
#2090
10
#2100
00
11
0.
#2110
10
#2120
00
01
#2125
0:
1.
#2130
10
#2140
00
11
#2150
10
0.
#2160
00
01
#2170
10
#2175
0;
1:
1.
#2180
00
11
#2190
10
#2200
00
01
0.
#2210
10
#2220
00
11
#2225
0:
1.
#2230
10
#2240
00
01
#2250
10
0.
#2260
00
11
#2270
10
#2275
0<
1;
1:
1.
#2280
00
01
#2290
10
#2300
00
11
0.
#2310
10
#2320
00
01
#2325
0:
1.
#2330
10
#2340
00
11
#2350
10
0.
#2360
00
01
#2370
10
#2375
0;
1:
1.
#2380
00
11
#2390
10
#2400
00
01
0.
#2410
10
#2420
00
11
#2425
0:
1.
#2430
10
#2440
00
01
#2450
10
0.
#2460
00
11
#2470
10
#2475
b100 8
0%
19
1<
1;
1:
1.
#2480
00
01
#2490
10
#2500
00
11
0.
#2510
10
#2520
00
01
#2525
0:
0A
1.
#2530
10
#2540
00
11
#2550
10
0.
#2560
00
01
#2570
10
#2575
0;
1:
1.
#2580
00
11
#2590
10
#2600
00
01
0.
#2610
10
#2620
00
11
#2625
0:
1.
#2630
10
#2640
00
01
#2650
10
0.
#2660
00
11
#2670
10
#2675
0<
1;
1:
1.
#2680
00
01
#2690
10
#2700
00
11
0.
#2710
10
#2720
00
01
#2725
0:
1.
#2730
10
#2740
00
11
#2750
10
0.
#2760
00
01
#2770
10
#2775
0;
1:
1.
#2780
00
11
#2790
10
#2800
00
01
0.
#2810
10
#2820
00
11
#2825
0:
1.
#2830
10
#2840
00
01
#2850
10
0.
#2860
00
11
#2870
10
#2875
09
1<
1;
1:
1.
#2880
00
01
#2890
10
#2900
00
11
0.
#2910
10
#2920
00
01
#2925
0:
1.
#2930
10
#2940
00
11
#2950
10
0.
#2960
00
01
#2970
10
#2975
0;
1:
1.
#2980
00
11
#2990
10
#3000
00
01
0.
#3010
10
#3020
00
11
#3025
0:
1.
#3030
10
#3040
00
01
#3050
10
0.
#3060
00
11
#3070
10
#3075
0<
1;
1:
1.
#3080
00
01
#3090
10
#3100
00
11
0.
#3110
10
#3120
00
01
#3125
0:
1.
#3130
10
#3140
00
11
#3150
10
0.
#3160
00
01
#3170
10
#3175
0;
1:
1.
#3180
00
11
#3190
10
#3200
00
01
0.
#3210
10
#3220
00
11
#3225
0:
1.
#3230
10
#3240
00
01
#3250
10
0.
#3260
00
11
#3270
10
#3275
1%
b101 8
19
1<
1;
1:
1.
#3280
00
01
#3290
10
#3300
00
11
0.
#3310
10
#3320
00
01
#3325
0:
1A
b10 =
b11000 B
1.
#3330
10
#3340
00
11
#3350
10
0.
#3360
00
01
#3370
10
#3375
0;
1:
1.
#3380
00
11
#3390
10
#3400
00
01
0.
#3410
10
#3420
00
11
#3425
0:
1.
#3430
10
#3440
00
01
#3450
10
0.
#3460
00
11
#3470
10
#3475
0<
1;
1:
1.
#3480
00
01
#3490
10
#3500
00
11
0.
#3510
10
#3520
00
01
#3525
0:
1.
#3530
10
#3540
00
11
#3550
10
0.
#3560
00
01
#3570
10
#3575
0;
1:
1.
#3580
00
11
#3590
10
#3600
00
01
0.
#3610
10
#3620
00
11
#3625
0:
1.
#3630
10
#3640
00
01
#3650
10
0.
#3660
00
11
#3670
10
#3675
09
1<
1;
1:
1.
#3680
00
01
#3690
10
#3700
00
11
0.
#3710
10
#3720
00
01
#3725
0:
1.
#3730
10
#3740
00
11
#3750
10
0.
#3760
00
01
#3770
10
#3775
0;
1:
1.
#3780
00
11
#3790
10
#3800
00
01
0.
#3810
10
#3820
00
11
#3825
0:
1.
#3830
10
#3840
00
01
#3850
10
0.
#3860
00
11
#3870
10
#3875
0<
1;
1:
1.
#3880
00
01
#3890
10
#3900
00
11
0.
#3910
10
#3920
00
01
#3925
0:
1.
#3930
10
#3940
00
11
#3950
10
0.
#3960
00
01
#3970
10
#3975
0;
1:
1.
#3980
00
11
#3990
10
#4000
00
01
0.
#4010
10
#4020
00
11
#4025
0:
1.
#4030
10
#4040
00
01
#4050
10
0.
#4060
00
11
#4070
10
#4075
0$
b110 8
0%
19
1<
1;
1:
1.
#4080
00
01
#4090
10
#4100
00
11
0.
#4110
10
#4120
00
01
#4125
0:
0A
1.
#4130
10
#4140
00
11
#4150
10
0.
#4160
00
01
#4170
10
#4175
0;
1:
1.
#4180
00
11
#4190
10
#4200
00
01
0.
#4210
10
#4220
00
11
#4225
0:
1.
#4230
10
#4240
00
01
#4250
10
0.
#4260
00
11
#4270
10
#4275
0<
1;
1:
1.
#4280
00
01
#4290
10
#4300
00
11
0.
#4310
10
#4320
00
01
#4325
0:
1.
#4330
10
#4340
00
11
#4350
10
0.
#4360
00
01
#4370
10
#4375
0;
1:
1.
#4380
00
11
#4390
10
#4400
00
01
0.
#4410
10
#4420
00
11
#4425
0:
1.
#4430
10
#4440
00
01
#4450
10
0.
#4460
00
11
#4470
10
#4475
09
1<
1;
1:
1.
#4480
00
01
#4490
10
#4500
00
11
0.
#4510
10
#4520
00
01
#4525
0:
1.
#4530
10
#4540
00
11
#4550
10
0.
#4560
00
01
#4570
10
#4575
0;
1:
1.
#4580
00
11
#4590
10
#4600
00
01
0.
#4610
10
#4620
00
11
#4625
0:
1.
#4630
10
#4640
00
01
#4650
10
0.
#4660
00
11
#4670
10
#4675
0<
1;
1:
1.
#4680
00
01
#4690
10
#4700
00
11
0.
#4710
10
#4720
00
01
#4725
0:
1.
#4730
10
#4740
00
11
#4750
10
0.
#4760
00
01
#4770
10
#4775
0;
1:
1.
#4780
00
11
#4790
10
#4800
00
01
0.
#4810
10
#4820
00
11
#4825
0:
1.
#4830
10
#4840
00
01
#4850
10
0.
#4860
00
11
#4870
10
#4875
1%
b111 8
19
1<
1;
1:
1.
#4880
00
01
#4890
10
#4900
00
11
0.
#4910
10
#4920
00
01
#4925
0:
1A
b11 =
1.
#4930
10
#4940
00
11
#4950
10
0.
#4960
00
01
#4970
10
#4975
0;
1:
1.
#4980
00
11
#4990
10
#5000
00
01
0.
#5010
10
#5020
00
11
#5025
0:
1.
#5030
10
#5040
00
01
#5050
10
0.
#5060
00
11
#5070
10
#5075
0<
1;
1:
1.
#5080
00
01
#5090
10
#5100
00
11
0.
#5110
10
#5120
00
01
#5125
0:
1.
#5130
10
#5140
00
11
#5150
10
0.
#5160
00
01
#5170
10
#5175
0;
1:
1.
#5180
00
11
#5190
10
#5200
00
01
0.
#5210
10
#5220
00
11
#5225
0:
1.
#5230
10
#5240
00
01
#5250
10
0.
#5260
00
11
#5270
10
#5275
09
1<
1;
1:
1.
#5280
00
01
#5290
10
#5300
00
11
0.
#5310
10
#5320
00
01
#5325
0:
1.
#5330
10
#5340
00
11
#5350
10
0.
#5360
00
01
#5370
10
#5375
0;
1:
1.
#5380
00
11
#5390
10
#5400
00
01
0.
#5410
10
#5420
00
11
#5425
0:
1.
#5430
10
#5440
00
01
#5450
10
0.
#5460
00
11
#5470
10
#5475
0<
1;
1:
1.
#5480
00
01
#5490
10
#5500
00
11
0.
#5510
10
#5520
00
01
#5525
0:
1.
#5530
10
#5540
00
11
#5550
10
0.
#5560
00
01
#5570
10
#5575
0;
1:
1.
#5580
00
11
#5590
10
#5600
00
01
0.
#5610
10
#5620
00
11
#5625
0:
1.
#5630
10
#5640
00
01
#5650
10
0.
#5660
00
11
#5670
10
#5675
b1000 8
0%
19
1<
1;
1:
1.
#5680
00
01
#5690
10
#5700
00
11
0.
#5710
10
#5720
00
01
#5725
0:
0A
1.
#5730
10
#5740
00
11
#5750
10
0.
#5760
00
01
#5770
10
#5775
0;
1:
1.
#5780
00
11
#5790
10
#5800
00
01
0.
#5810
10
#5820
00
11
#5825
0:
1.
#5830
10
#5840
00
01
#5850
10
0.
#5860
00
11
#5870
10
#5875
0<
1;
1:
1.
#5880
00
01
#5890
10
#5900
00
11
0.
#5910
10
#5920
00
01
#5925
0:
1.
#5930
10
#5940
00
11
#5950
10
0.
#5960
00
01
#5970
10
#5975
0;
1:
1.
#5980
00
11
#5990
10
#6000
00
01
0.
#6010
10
#6020
00
11
#6025
0:
1.
#6030
10
#6040
00
01
#6050
10
0.
#6060
00
11
#6070
10
#6075
09
1<
1;
1:
1.
#6080
00
01
#6090
10
#6100
00
11
0.
#6110
10
#6120
00
01
#6125
0:
1.
#6130
10
#6140
00
11
#6150
10
0.
#6160
00
01
#6170
10
#6175
0;
1:
1.
#6180
00
11
#6190
10
#6200
00
01
0.
#6210
10
#6220
00
11
#6225
0:
1.
#6230
10
#6240
00
01
#6250
10
0.
#6260
00
11
#6270
10
#6275
0<
1;
1:
1.
#6280
00
01
#6290
10
#6300
00
11
0.
#6310
10
#6320
00
01
#6325
0:
1.
#6330
10
#6340
00
11
#6350
10
0.
#6360
00
01
#6370
10
#6375
0;
1:
1.
#6380
00
11
#6390
10
#6400
00
01
0.
#6410
10
#6420
00
11
#6425
0:
1.
#6430
10
#6440
00
01
#6450
10
0.
#6460
00
11
#6470
10
#6475
1%
b1001 8
19
1<
1;
1:
1.
#6480
00
01
#6490
10
#6500
00
11
0.
#6510
10
#6520
00
01
#6525
0:
1A
b100 =
1.
#6530
10
#6540
00
11
#6550
10
0.
#6560
00
01
#6570
10
#6575
0;
1:
1.
#6580
00
11
#6590
10
#6600
00
01
0.
#6610
10
#6620
00
11
#6625
0:
1.
#6630
10
#6640
00
01
#6650
10
0.
#6660
00
11
#6670
10
#6675
0<
1;
1:
1.
#6680
00
01
#6690
10
#6700
00
11
0.
#6710
10
#6720
00
01
#6725
0:
1.
#6730
10
#6740
00
11
#6750
10
0.
#6760
00
01
#6770
10
#6775
0;
1:
1.
#6780
00
11
#6790
10
#6800
00
01
0.
#6810
10
#6820
00
11
#6825
0:
1.
#6830
10
#6840
00
01
#6850
10
0.
#6860
00
11
#6870
10
#6875
09
1<
1;
1:
1.
#6880
00
01
#6890
10
#6900
00
11
0.
#6910
10
#6920
00
01
#6925
0:
1.
#6930
10
#6940
00
11
#6950
10
0.
#6960
00
01
#6970
10
#6975
0;
1:
1.
#6980
00
11
#6990
10
#7000
00
01
0.
#7010
10
#7020
00
11
#7025
0:
1.
#7030
10
#7040
00
01
#7050
10
0.
#7060
00
11
#7070
10
#7075
0<
1;
1:
1.
#7080
00
01
#7090
10
#7100
00
11
0.
#7110
10
#7120
00
01
#7125
0:
1.
#7130
10
#7140
00
11
#7150
10
0.
#7160
00
01
#7170
10
#7175
0;
1:
1.
#7180
00
11
#7190
10
#7200
00
01
0.
#7210
10
#7220
00
11
#7225
0:
1.
#7230
10
#7240
00
01
#7250
10
0.
#7260
00
11
#7270
10
#7275
1$
b1010 8
0%
19
1<
1;
1:
1.
#7280
00
01
#7290
10
#7300
00
11
0.
#7310
10
#7320
00
01
#7325
0:
b10 7
0A
1.
#7330
10
#7340
00
11
#7350
10
0.
#7360
00
01
#7370
10
#7375
0;
1:
1.
#7380
00
11
#7390
10
#7400
00
01
0.
#7410
10
#7420
00
11
#7425
0:
1.
#7430
10
#7440
00
01
#7450
10
0.
#7460
00
11
#7470
10
#7475
0<
1;
1:
1.
#7480
00
01
#7490
10
#7500
00
11
0.
#7510
10
#7520
00
01
#7525
0:
1.
#7530
10
#7540
00
11
#7550
10
0.
#7560
00
01
#7570
10
#7575
0;
1:
1.
#7580
00
11
#7590
10
#7600
00
01
0.
#7610
10
#7620
00
11
#7625
0:
1.
#7630
10
#7640
00
01
#7650
10
0.
#7660
00
11
#7670
10
#7675
09
1<
1;
1:
1.
#7680
00
01
#7690
10
#7700
00
11
0.
#7710
10
#7720
00
01
#7725
0:
1.
#7730
10
#7740
00
11
#7750
10
0.
#7760
00
01
#7770
10
#7775
0;
1:
1.
#7780
00
11
#7790
10
#7800
00
01
0.
#7810
10
#7820
00
11
#7825
0:
1.
#7830
10
#7840
00
01
#7850
10
0.
#7860
00
11
#7870
10
#7875
0<
1;
1:
1.
#7880
00
01
#7890
10
#7900
00
11
0.
#7910
10
#7920
00
01
#7925
0:
1.
#7930
10
#7940
00
11
#7950
10
0.
#7960
00
01
#7970
10
#7975
0;
1:
1.
#7980
00
11
#7990
10
#8000
00
01
0.
#8010
10
#8020
00
11
#8025
0:
1.
#8030
10
#8040
00
01
#8050
10
0.
#8060
00
11
#8070
10
#8075
1%
19
1<
1;
1:
1.
#8080
00
01
#8090
10
#8100
00
11
0.
#8110
10
#8120
00
01
#8125
0:
1A
b101 =
b11001 B
1.
#8130
10
#8140
00
11
#8150
10
0.
#8160
00
01
#8170
10
#8175
0;
1:
b1 C
b110 -
b110 ?
b1 ,
b1 @
b0 =
1.
#8180
00
11
#8190
10
#8200
00
01
0.
#8210
10
#8220
00
11
#8225
0:
b1 =
1.
#8230
10
#8240
00
01
#8250
10
0.
#8260
00
11
#8270
10
#8275
0<
1;
1:
b10 =
1.
#8280
00
01
#8290
10
#8300
00
11
0.
#8310
10
#8320
00
01
#8325
0:
b11 =
1.
#8330
10
#8340
00
11
#8350
10
0.
#8360
00
01
#8370
10
#8375
0;
1:
b100 =
1.
#8380
00
11
#8390
10
#8400
00
01
0.
#8410
10
#8420
00
11
#8425
0:
b10 C
b0 =
1.
#8430
10
#8440
00
01
#8450
10
0.
#8460
00
11
#8470
10
#8475
09
1<
b1 E
b1 D
1;
1!
1#
1:
b11 C
1&
1'
1.
#8480
0#
0!
00
01
#8490
b10 D
1#
10
#8500
b10 E
0#
1!
00
11
0.
#8510
b11 D
1#
10
