backend.v
module backend(
    input i_resetbAll,
    input i_clk,
    input i_sclk,
    input i_sdin,
    input i_clk_vco1,
    input i_clk_vco2,
    output reg o_ready,
    output reg o_vco1_fast,
    output reg o_resetb1,
    output reg [2:0] o_gainA1,
    output reg o_resetb2,
    output reg [1:0] o_gainA2,
    output reg o_resetbvco1,
    output reg o_resetbvco2
);

reg [4:0] counter1;
reg [7:0] vco1_counter;
reg [7:0] vco2_counter;
reg [4:0] startup_state;
reg [4:0] shift_register;
reg prev_isclk;

always @(posedge i_clk or negedge i_resetbAll) begin
    if (!i_resetbAll) begin
        // Reset the entire backend
        counter1 <= 0;
        vco1_counter <= 0;
        vco2_counter <=0;
        startup_state <= 0;
        shift_register <= 0;
        o_resetb1 <= 1'b0;
        o_resetb2 <= 1'b0;
        o_gainA1 <= 3'b000;
        o_gainA2 <= 2'b00;
        o_resetbvco1 <= 1'b0;
        o_resetbvco2 <= 1'b0;
        o_ready <= 1'b0;
        o_vco1_fast <= 1'b1;
        prev_isclk <= 1'b1;
    end else begin
        // State machine for the startup sequence
        case(startup_state)
            0: begin
                if (counter1 < 5) begin
                    if(i_sclk&&!prev_isclk)begin
                        shift_register[4-counter1] <=i_sdin;
                        counter1 <= counter1 +1;
                    end
                end else begin
                    counter1 <= 0;
                    o_gainA2 <= shift_register[1:0];
                    o_gainA1 <= shift_register[4:2];
                    startup_state <= 1;
                end
                prev_isclk <= i_sclk;
            end
            1: begin
                // Wait for five clock cycles
                if (counter1 < 4) begin
                    counter1 <= counter1 + 1;
                end else begin
                    counter1 <= 0;
                    startup_state <= 2;
                end
            end
            2: begin
                // Set o_resetbvco1 and o_resetbvco2
                o_resetbvco1 <= 1'b1;
                o_resetbvco2 <= 1'b1;
                startup_state <= 3;
            end
            3: begin
                // Wait for 20 clock cycles
                if (counter1 < 20) begin
                    counter1 <= counter1 + 1;
                end else begin
                    counter1 <= 0;
                    startup_state <= 4;
                end
            end
            4: begin
                // Set o_resetb1 and o_resetb2
                o_resetb1 <= 1'b1;
                o_resetb2 <= 1'b1;
                startup_state <= 5;
            end
            5: begin
                // Wait for 10 clock cycles
                if (counter1 < 10) begin
                    counter1 <= counter1 + 1;
                end else begin
                    startup_state <= 6;
                    counter1 <= 0;
                end
            end
            6: begin
                //Compare both the clocks and pull up o_vco1_fast if first vco is faster than second vco
                
                if (vco1_counter >= vco2_counter)begin
                    o_vco1_fast <= 1'b1;
                end else begin
                    
                    o_vco1_fast <= 0;                    

                end
                
                
                // Set o_ready
                o_ready <= 1'b1;
                startup_state <= 7;
                
            end
            default: begin
                // No more actions required, hold values
            end
        endcase

        
    end
end

always @(posedge i_clk_vco1)begin
    if (startup_state < 7)begin
        vco1_counter <= vco1_counter + 1;
    end
    else begin
        vco1_counter <= 0;
    end
end

always @(posedge i_clk_vco2)begin
    if (startup_state < 7)begin
        vco2_counter <= vco2_counter + 1;
    end
    else begin
        vco2_counter <= 0;
    end
end

endmodule

FPGA_model.v
///////////////////////////////////////////////////////////////////////////////
/*FPGA model
 * Generates reset signal for the chip
 * Sends out progamming bits to the chip
*/
module FPGA_model(	i_resetbFPGA,
			i_ready,
			i_mainclk,
			i_vco1_fast,
			o_resetbAll,
			o_sclk, 
			o_sdout);

//============================================================================
//Parameter declarations
parameter opcode_gainA1	= 6; //range: 0-7. Gain for amplifier 1
parameter opcode_gainA2	= 1; //range: 0-3. Gain for amplifier 2

//FPGA states
parameter sRESET 	= 0; //Reset all internal variables. Make o_resetbAll=0.
parameter sPROGRAM	= 1; //Send programming bits to chip.
parameter sIDLE		= 2; //Do nothing.
//===========================================================================
//Input output declarations
input i_resetbFPGA; 		//resets FPGA
input i_ready;			//Alerts FPGA that chip is programmed and ready
input i_mainclk;		//Main clock
input i_vco1_fast;		//Goes high when vco1 is faster than vco2
output reg o_resetbAll;		//Reset for the chip
output reg o_sclk;		//Serial clock for communication
output reg o_sdout;		//Serial data out from FPGA (to chip)


//Internal wire, reg declarations
reg [1:0] FPGAstate;		//Holds the state of FPGA
reg [3:0] count;		//Used for controlling sclk generation and transmission of serial data
reg mainclkby2, mainclkby4, mainclkby8, mainclkby16; //Low frequency clocks derived from mainclk

//=============================================================
//BEHAVIORAL DESCRIPTION
//=============================================================
// Setting the FPGA state
always @ (posedge(i_mainclk) or negedge(i_resetbFPGA))
begin
	if(i_resetbFPGA == 0)
		FPGAstate <= sRESET;
	else
	begin
		case(FPGAstate)
		sRESET: FPGAstate <= sPROGRAM;
		sPROGRAM: 
		begin	
			if(count== 10)
				FPGAstate <= sIDLE;
			else
				FPGAstate <= sPROGRAM;
		end
		sIDLE: FPGAstate <=sIDLE;
		default: FPGAstate <= sIDLE;
		endcase
	end
end
//========================================================
/*resetbALL
 * resetbAll=0, when FPGA is reset. 
 * resetbAll=1 at all other times.
*/
always @(posedge(i_mainclk) or negedge(i_resetbFPGA))
begin
	if(i_resetbFPGA == 0)
		o_resetbAll <= 0;
	else
	begin
		if(FPGAstate == sRESET)
			o_resetbAll <= 0;
		else
			o_resetbAll <= 1;
	end
end
//==========================================================
/* Generation of low frequency clocks from mainclk using divide-by-2 method
*/
always @ (posedge(i_mainclk) or negedge(i_resetbFPGA))
begin
	if(i_resetbFPGA == 0)
		mainclkby2 <= 0;
	else
		mainclkby2 <= ~mainclkby2;
end

always @ (posedge(mainclkby2) or negedge(i_resetbFPGA))
begin
	if(i_resetbFPGA == 0)
		mainclkby4 <= 0;
	else
		mainclkby4 <= ~mainclkby4;
end

always @(posedge(mainclkby4) or negedge(i_resetbFPGA))
begin
	if(i_resetbFPGA == 0)
		mainclkby8 <= 0;
	else
		mainclkby8 <= ~mainclkby8;
end

always @(posedge(mainclkby8) or negedge(i_resetbFPGA))
begin
	if(i_resetbFPGA == 0)
		mainclkby16 <= 0;
	else
		mainclkby16 <= ~mainclkby16;
end
//==========================================================
/*count
 * used for the generation of sclk and selecting the data to be sent in through sdin
 */
always	@(posedge(mainclkby16) or negedge(i_resetbFPGA))
begin
	if(i_resetbFPGA == 0)
		count <= 0;
	else
	begin
		if(FPGAstate == sPROGRAM)
		begin
			if(count == 11)
				count <= count;
			else
				count <= count+1;
		end
		else
			count <= count;
	end
end
//=========================================================
/*sclk
 * sclk is a clock only when the FPGA is programming the chip.
 */
always @ (posedge(mainclkby16) or negedge(i_resetbFPGA))
begin
	if(i_resetbFPGA == 0)
		o_sclk <= 1;
	else
	begin
		if(FPGAstate == sPROGRAM)
		begin
			if (count >= 1 && count <= 10)
				o_sclk <= ~o_sclk;
			else
				o_sclk <= 1;
		end
		else
			o_sclk <= 1;
	end
end

//=========================================================
/*sdin
 *serial data out from FPGA
 */
always @ (negedge(o_sclk) or negedge(i_resetbFPGA))
begin
	if(i_resetbFPGA == 0)
		o_sdout <= 0;
	else
	begin
		if(FPGAstate == sPROGRAM)
		begin
			case(count)
			4'd2: o_sdout <= opcode_gainA1[2];
			4'd4: o_sdout <= opcode_gainA1[1];
			4'd6: o_sdout <= opcode_gainA1[0];
			4'd8: o_sdout <= opcode_gainA2[1];
			4'd10: o_sdout <= opcode_gainA2[0];
			default: o_sdout <= o_sdout;
			endcase
		end
		else
			o_sdout <= 0;
		
	end
end
//==========================================================
endmodule

backend_tb.v
// Testbanch module for the backend. This is has a module instantiation for
// the FPGA_model and the backend.
`timescale 1ns / 100ps
//==========================================================================
//Change the Verilog filenames approppriately.
`include "FPGA_model.v"
`include "backend.v"
//=========================================================================

module backend_tb();

reg resetbFPGA;
reg main_clk;
reg vco1_clockmodel, vco2_clockmodel; 

wire [2:0]gainA1 ; 
wire [1:0]gainA2 ;
wire resetbAll, resetb1, resetb2, resetbvco1, resetbvco2; 
wire vco1_clk, vco2_clk;
wire sclk, sdin;
wire ready;
wire vco1_fast;


//==========================================================================
//FPGA model instantiation
FPGA_model   FPGA_obj(	.i_resetbFPGA (resetbFPGA),
			.i_ready (ready),
			.o_resetbAll (resetbAll),
			.i_mainclk (main_clk),
			.o_sclk (sclk), 
			.o_sdout (sdin),
			.i_vco1_fast (vco1_fast) );

// Backend instantiation 
backend backend_obj (	.i_resetbAll (resetbAll),
			.i_clk (main_clk),
			.i_sclk (sclk),
			.i_sdin (sdin),
			.i_clk_vco1 (vco1_clk),
			.i_clk_vco2 (vco2_clk),
			.o_ready (ready),
                        .o_vco1_fast (vco1_fast),
			.o_resetb1 (resetb1),
			.o_gainA1 (gainA1),
			.o_resetb2 (resetb2),
			.o_gainA2 (gainA2),
			.o_resetbvco1 (resetbvco1),
			.o_resetbvco2 (resetbvco2)
			);
//============================================================================
// VCO clock model
assign vco1_clk = (resetbvco1)?vco1_clockmodel:0;
assign vco2_clk = (resetbvco2)?vco2_clockmodel:0;

//============================================================================

//Test signal generation
initial
begin
	$dumpfile("backend_tb.vcd"); // Specify the VCD file name
    $dumpvars(0, backend_tb);  
	resetbFPGA <= 0;
	main_clk <= 0;
	vco1_clockmodel <= 0;
	vco2_clockmodel <= 0;
	#4 resetbFPGA <= 1;
	#1500;
    $finish;
	
end

//Generation of main_clk 
always #2.5 main_clk <= ~main_clk;

//Generation of internal clock models for the VCOs
always #2.5 vco1_clockmodel <= ~vco1_clockmodel;
always #2 vco2_clockmodel <= ~vco2_clockmodel;


//============================================================================
endmodule

backend_tb.vcd
$date
	Fri Oct 27 09:15:37 2023
$end
$version
	Icarus Verilog
$end
$timescale
	100ps
$end
$scope module backend_tb $end
$var wire 1 ! vco2_clk $end
$var wire 1 " vco1_fast $end
$var wire 1 # vco1_clk $end
$var wire 1 $ sdin $end
$var wire 1 % sclk $end
$var wire 1 & resetbvco2 $end
$var wire 1 ' resetbvco1 $end
$var wire 1 ( resetbAll $end
$var wire 1 ) resetb2 $end
$var wire 1 * resetb1 $end
$var wire 1 + ready $end
$var wire 2 , gainA2 [1:0] $end
$var wire 3 - gainA1 [2:0] $end
$var reg 1 . main_clk $end
$var reg 1 / resetbFPGA $end
$var reg 1 0 vco1_clockmodel $end
$var reg 1 1 vco2_clockmodel $end
$scope module FPGA_obj $end
$var wire 1 . i_mainclk $end
$var wire 1 / i_resetbFPGA $end
$var wire 1 " i_vco1_fast $end
$var wire 1 + i_ready $end
$var parameter 32 2 opcode_gainA1 $end
$var parameter 32 3 opcode_gainA2 $end
$var parameter 32 4 sIDLE $end
$var parameter 32 5 sPROGRAM $end
$var parameter 32 6 sRESET $end
$var reg 2 7 FPGAstate [1:0] $end
$var reg 4 8 count [3:0] $end
$var reg 1 9 mainclkby16 $end
$var reg 1 : mainclkby2 $end
$var reg 1 ; mainclkby4 $end
$var reg 1 < mainclkby8 $end
$var reg 1 ( o_resetbAll $end
$var reg 1 % o_sclk $end
$var reg 1 $ o_sdout $end
$upscope $end
$scope module backend_obj $end
$var wire 1 . i_clk $end
$var wire 1 # i_clk_vco1 $end
$var wire 1 ! i_clk_vco2 $end
$var wire 1 ( i_resetbAll $end
$var wire 1 % i_sclk $end
$var wire 1 $ i_sdin $end
$var reg 5 = counter1 [4:0] $end
$var reg 3 > o_gainA1 [2:0] $end
$var reg 2 ? o_gainA2 [1:0] $end
$var reg 1 + o_ready $end
$var reg 1 * o_resetb1 $end
$var reg 1 ) o_resetb2 $end
$var reg 1 ' o_resetbvco1 $end
$var reg 1 & o_resetbvco2 $end
$var reg 1 " o_vco1_fast $end
$var reg 1 @ prev_isclk $end
$var reg 5 A shift_register [4:0] $end
$var reg 5 B startup_state [4:0] $end
$var reg 8 C vco1_counter [7:0] $end
$var reg 8 D vco2_counter [7:0] $end
$upscope $end
$upscope $end
$enddefinitions $end
$comment Show the parameter values. $end
$dumpall
b0 6
b1 5
b10 4
b1 3
b110 2
$end
#0
$dumpvars
b0 D
b0 C
b0 B
b0 A
1@
b0 ?
b0 >
b0 =
0<
0;
0:
09
b0 8
b0 7
01
00
0/
0.
b0 -
b0 ,
0+
0*
0)
0(
0'
0&
1%
0$
0#
1"
0!
$end
#22
11
#25
10
1.
#40
1/
#44
01
#50
00
0.
#66
11
#75
b1 8
19
1<
1;
b1 7
1:
10
1.
#88
01
#100
00
0.
#110
11
#125
0:
1(
10
1.
#132
01
#150
00
0.
#154
11
#175
0;
1:
10
1.
#176
01
#198
11
#200
00
0.
#220
01
#225
0:
10
1.
#242
11
#250
00
0.
#264
01
#275
0<
1;
1:
10
1.
#286
11
#300
00
0.
#308
01
#325
0:
10
1.
#330
11
#350
00
0.
#352
01
#374
11
#375
0;
1:
10
1.
#396
01
#400
00
0.
#418
11
#425
0:
10
1.
#440
01
#450
00
0.
#462
11
#475
09
1<
1;
1:
10
1.
#484
01
#500
00
0.
#506
11
#525
0:
10
1.
#528
01
#550
11
00
0.
#572
01
#575
0;
1:
10
1.
#594
11
#600
00
0.
#616
01
#625
0:
10
1.
#638
11
#650
00
0.
#660
01
#675
0<
1;
1:
10
1.
#682
11
#700
00
0.
#704
01
#725
0:
10
1.
#726
11
#748
01
#750
00
0.
#770
11
#775
0;
1:
10
1.
#792
01
#800
00
0.
#814
11
#825
0:
10
1.
#836
01
#850
00
0.
#858
11
#875
1$
b10 8
0%
19
1<
1;
1:
10
1.
#880
01
#900
00
0.
#902
11
#924
01
#925
0:
0@
10
1.
#946
11
#950
00
0.
#968
01
#975
0;
1:
10
1.
#990
11
#1000
00
0.
#1012
01
#1025
0:
10
1.
#1034
11
#1050
00
0.
#1056
01
#1075
0<
1;
1:
10
1.
#1078
11
#1100
01
00
0.
#1122
11
#1125
0:
10
1.
#1144
01
#1150
00
0.
#1166
11
#1175
0;
1:
10
1.
#1188
01
#1200
00
0.
#1210
11
#1225
0:
10
1.
#1232
01
#1250
00
0.
#1254
11
#1275
09
1<
1;
1:
10
1.
#1276
01
#1298
11
#1300
00
0.
#1320
01
#1325
0:
10
1.
#1342
11
#1350
00
0.
#1364
01
#1375
0;
1:
10
1.
#1386
11
#1400
00
0.
#1408
01
#1425
0:
10
1.
#1430
11
#1450
00
0.
#1452
01
#1474
11
#1475
0<
1;
1:
10
1.
#1496
01
#1500
00
0.
#1518
11
#1525
0:
10
1.
#1540
01
#1550
00
0.
#1562
11
#1575
0;
1:
10
1.
#1584
01
#1600
00
0.
#1606
11
#1625
0:
10
1.
#1628
01
#1650
11
00
0.
#1672
01
#1675
1%
b11 8
19
1<
1;
1:
10
1.
#1694
11
#1700
00
0.
#1716
01
#1725
0:
1@
b1 =
b10000 A
10
1.
#1738
11
#1750
00
0.
#1760
01
#1775
0;
1:
10
1.
#1782
11
#1800
00
0.
#1804
01
#1825
0:
10
1.
#1826
11
#1848
01
#1850
00
0.
#1870
11
#1875
0<
1;
1:
10
1.
#1892
01
#1900
00
0.
#1914
11
#1925
0:
10
1.
#1936
01
#1950
00
0.
#1958
11
#1975
0;
1:
10
1.
#1980
01
#2000
00
0.
#2002
11
#2024
01
#2025
0:
10
1.
#2046
11
#2050
00
0.
#2068
01
#2075
09
1<
1;
1:
10
1.
#2090
11
#2100
00
0.
#2112
01
#2125
0:
10
1.
#2134
11
#2150
00
0.
#2156
01
#2175
0;
1:
10
1.
#2178
11
#2200
01
00
0.
#2222
11
#2225
0:
10
1.
#2244
01
#2250
00
0.
#2266
11
#2275
0<
1;
1:
10
1.
#2288
01
#2300
00
0.
#2310
11
#2325
0:
10
1.
#2332
01
#2350
00
0.
#2354
11
#2375
0;
1:
10
1.
#2376
01
#2398
11
#2400
00
0.
#2420
01
#2425
0:
10
1.
#2442
11
#2450
00
0.
#2464
01
#2475
b100 8
0%
19
1<
1;
1:
10
1.
#2486
11
#2500
00
0.
#2508
01
#2525
0:
0@
10
1.
#2530
11
#2550
00
0.
#2552
01
#2574
11
#2575
0;
1:
10
1.
#2596
01
#2600
00
0.
#2618
11
#2625
0:
10
1.
#2640
01
#2650
00
0.
#2662
11
#2675
0<
1;
1:
10
1.
#2684
01
#2700
00
0.
#2706
11
#2725
0:
10
1.
#2728
01
#2750
11
00
0.
#2772
01
#2775
0;
1:
10
1.
#2794
11
#2800
00
0.
#2816
01
#2825
0:
10
1.
#2838
11
#2850
00
0.
#2860
01
#2875
09
1<
1;
1:
10
1.
#2882
11
#2900
00
0.
#2904
01
#2925
0:
10
1.
#2926
11
#2948
01
#2950
00
0.
#2970
11
#2975
0;
1:
10
1.
#2992
01
#3000
00
0.
#3014
11
#3025
0:
10
1.
#3036
01
#3050
00
0.
#3058
11
#3075
0<
1;
1:
10
1.
#3080
01
#3100
00
0.
#3102
11
#3124
01
#3125
0:
10
1.
#3146
11
#3150
00
0.
#3168
01
#3175
0;
1:
10
1.
#3190
11
#3200
00
0.
#3212
01
#3225
0:
10
1.
#3234
11
#3250
00
0.
#3256
01
#3275
1%
b101 8
19
1<
1;
1:
10
1.
#3278
11
#3300
01
00
0.
#3322
11
#3325
0:
1@
b10 =
b11000 A
10
1.
#3344
01
#3350
00
0.
#3366
11
#3375
0;
1:
10
1.
#3388
01
#3400
00
0.
#3410
11
#3425
0:
10
1.
#3432
01
#3450
00
0.
#3454
11
#3475
0<
1;
1:
10
1.
#3476
01
#3498
11
#3500
00
0.
#3520
01
#3525
0:
10
1.
#3542
11
#3550
00
0.
#3564
01
#3575
0;
1:
10
1.
#3586
11
#3600
00
0.
#3608
01
#3625
0:
10
1.
#3630
11
#3650
00
0.
#3652
01
#3674
11
#3675
09
1<
1;
1:
10
1.
#3696
01
#3700
00
0.
#3718
11
#3725
0:
10
1.
#3740
01
#3750
00
0.
#3762
11
#3775
0;
1:
10
1.
#3784
01
#3800
00
0.
#3806
11
#3825
0:
10
1.
#3828
01
#3850
11
00
0.
#3872
01
#3875
0<
1;
1:
10
1.
#3894
11
#3900
00
0.
#3916
01
#3925
0:
10
1.
#3938
11
#3950
00
0.
#3960
01
#3975
0;
1:
10
1.
#3982
11
#4000
00
0.
#4004
01
#4025
0:
10
1.
#4026
11
#4048
01
#4050
00
0.
#4070
11
#4075
0$
b110 8
0%
19
1<
1;
1:
10
1.
#4092
01
#4100
00
0.
#4114
11
#4125
0:
0@
10
1.
#4136
01
#4150
00
0.
#4158
11
#4175
0;
1:
10
1.
#4180
01
#4200
00
0.
#4202
11
#4224
01
#4225
0:
10
1.
#4246
11
#4250
00
0.
#4268
01
#4275
0<
1;
1:
10
1.
#4290
11
#4300
00
0.
#4312
01
#4325
0:
10
1.
#4334
11
#4350
00
0.
#4356
01
#4375
0;
1:
10
1.
#4378
11
#4400
01
00
0.
#4422
11
#4425
0:
10
1.
#4444
01
#4450
00
0.
#4466
11
#4475
09
1<
1;
1:
10
1.
#4488
01
#4500
00
0.
#4510
11
#4525
0:
10
1.
#4532
01
#4550
00
0.
#4554
11
#4575
0;
1:
10
1.
#4576
01
#4598
11
#4600
00
0.
#4620
01
#4625
0:
10
1.
#4642
11
#4650
00
0.
#4664
01
#4675
0<
1;
1:
10
1.
#4686
11
#4700
00
0.
#4708
01
#4725
0:
10
1.
#4730
11
#4750
00
0.
#4752
01
#4774
11
#4775
0;
1:
10
1.
#4796
01
#4800
00
0.
#4818
11
#4825
0:
10
1.
#4840
01
#4850
00
0.
#4862
11
#4875
1%
b111 8
19
1<
1;
1:
10
1.
#4884
01
#4900
00
0.
#4906
11
#4925
0:
1@
b11 =
10
1.
#4928
01
#4950
11
00
0.
#4972
01
#4975
0;
1:
10
1.
#4994
11
#5000
00
0.
#5016
01
#5025
0:
10
1.
#5038
11
#5050
00
0.
#5060
01
#5075
0<
1;
1:
10
1.
#5082
11
#5100
00
0.
#5104
01
#5125
0:
10
1.
#5126
11
#5148
01
#5150
00
0.
#5170
11
#5175
0;
1:
10
1.
#5192
01
#5200
00
0.
#5214
11
#5225
0:
10
1.
#5236
01
#5250
00
0.
#5258
11
#5275
09
1<
1;
1:
10
1.
#5280
01
#5300
00
0.
#5302
11
#5324
01
#5325
0:
10
1.
#5346
11
#5350
00
0.
#5368
01
#5375
0;
1:
10
1.
#5390
11
#5400
00
0.
#5412
01
#5425
0:
10
1.
#5434
11
#5450
00
0.
#5456
01
#5475
0<
1;
1:
10
1.
#5478
11
#5500
01
00
0.
#5522
11
#5525
0:
10
1.
#5544
01
#5550
00
0.
#5566
11
#5575
0;
1:
10
1.
#5588
01
#5600
00
0.
#5610
11
#5625
0:
10
1.
#5632
01
#5650
00
0.
#5654
11
#5675
b1000 8
0%
19
1<
1;
1:
10
1.
#5676
01
#5698
11
#5700
00
0.
#5720
01
#5725
0:
0@
10
1.
#5742
11
#5750
00
0.
#5764
01
#5775
0;
1:
10
1.
#5786
11
#5800
00
0.
#5808
01
#5825
0:
10
1.
#5830
11
#5850
00
0.
#5852
01
#5874
11
#5875
0<
1;
1:
10
1.
#5896
01
#5900
00
0.
#5918
11
#5925
0:
10
1.
#5940
01
#5950
00
0.
#5962
11
#5975
0;
1:
10
1.
#5984
01
#6000
00
0.
#6006
11
#6025
0:
10
1.
#6028
01
#6050
11
00
0.
#6072
01
#6075
09
1<
1;
1:
10
1.
#6094
11
#6100
00
0.
#6116
01
#6125
0:
10
1.
#6138
11
#6150
00
0.
#6160
01
#6175
0;
1:
10
1.
#6182
11
#6200
00
0.
#6204
01
#6225
0:
10
1.
#6226
11
#6248
01
#6250
00
0.
#6270
11
#6275
0<
1;
1:
10
1.
#6292
01
#6300
00
0.
#6314
11
#6325
0:
10
1.
#6336
01
#6350
00
0.
#6358
11
#6375
0;
1:
10
1.
#6380
01
#6400
00
0.
#6402
11
#6424
01
#6425
0:
10
1.
#6446
11
#6450
00
0.
#6468
01
#6475
1%
b1001 8
19
1<
1;
1:
10
1.
#6490
11
#6500
00
0.
#6512
01
#6525
0:
1@
b100 =
10
1.
#6534
11
#6550
00
0.
#6556
01
#6575
0;
1:
10
1.
#6578
11
#6600
01
00
0.
#6622
11
#6625
0:
10
1.
#6644
01
#6650
00
0.
#6666
11
#6675
0<
1;
1:
10
1.
#6688
01
#6700
00
0.
#6710
11
#6725
0:
10
1.
#6732
01
#6750
00
0.
#6754
11
#6775
0;
1:
10
1.
#6776
01
#6798
11
#6800
00
0.
#6820
01
#6825
0:
10
1.
#6842
11
#6850
00
0.
#6864
01
#6875
09
1<
1;
1:
10
1.
#6886
11
#6900
00
0.
#6908
01
#6925
0:
10
1.
#6930
11
#6950
00
0.
#6952
01
#6974
11
#6975
0;
1:
10
1.
#6996
01
#7000
00
0.
#7018
11
#7025
0:
10
1.
#7040
01
#7050
00
0.
#7062
11
#7075
0<
1;
1:
10
1.
#7084
01
#7100
00
0.
#7106
11
#7125
0:
10
1.
#7128
01
#7150
11
00
0.
#7172
01
#7175
0;
1:
10
1.
#7194
11
#7200
00
0.
#7216
01
#7225
0:
10
1.
#7238
11
#7250
00
0.
#7260
01
#7275
1$
b1010 8
0%
19
1<
1;
1:
10
1.
#7282
11
#7300
00
0.
#7304
01
#7325
0:
b10 7
0@
10
1.
#7326
11
#7348
01
#7350
00
0.
#7370
11
#7375
0;
1:
10
1.
#7392
01
#7400
00
0.
#7414
11
#7425
0:
10
1.
#7436
01
#7450
00
0.
#7458
11
#7475
0<
1;
1:
10
1.
#7480
01
#7500
00
0.
#7502
11
#7524
01
#7525
0:
10
1.
#7546
11
#7550
00
0.
#7568
01
#7575
0;
1:
10
1.
#7590
11
#7600
00
0.
#7612
01
#7625
0:
10
1.
#7634
11
#7650
00
0.
#7656
01
#7675
09
1<
1;
1:
10
1.
#7678
11
#7700
01
00
0.
#7722
11
#7725
0:
10
1.
#7744
01
#7750
00
0.
#7766
11
#7775
0;
1:
10
1.
#7788
01
#7800
00
0.
#7810
11
#7825
0:
10
1.
#7832
01
#7850
00
0.
#7854
11
#7875
0<
1;
1:
10
1.
#7876
01
#7898
11
#7900
00
0.
#7920
01
#7925
0:
10
1.
#7942
11
#7950
00
0.
#7964
01
#7975
0;
1:
10
1.
#7986
11
#8000
00
0.
#8008
01
#8025
0:
10
1.
#8030
11
#8050
00
0.
#8052
01
#8074
11
#8075
1%
19
1<
1;
1:
10
1.
#8096
01
#8100
00
0.
#8118
11
#8125
0:
1@
b101 =
b11001 A
10
1.
#8140
01
#8150
00
0.
#8162
11
#8175
0;
1:
b1 B
b110 -
b110 >
b1 ,
b1 ?
b0 =
10
1.
#8184
01
#8200
00
0.
#8206
11
#8225
0:
b1 =
10
1.
#8228
01
#8250
11
00
0.
#8272
01
#8275
0<
1;
1:
b10 =
10
1.
#8294
11
#8300
00
0.
#8316
01
#8325
0:
b11 =
10
1.
#8338
11
#8350
00
0.
#8360
01
#8375
0;
1:
b100 =
10
1.
#8382
11
#8400
00
0.
#8404
01
#8425
0:
b10 B
b0 =
10
1.
#8426
11
#8448
01
#8450
00
0.
#8470
11
#8475
09
1<
b1 D
b1 C
1;
1!
1#
1:
b11 B
1&
1'
10
1.
#8492
0!
01
#8500
0#
00
0.
#8514
b10 D
1!
11
#8525
b10 C
0:
b1 =
1#
10
1.
#8536
0!
01
#8550
0#
00
0.
#8558
b11 D
1!
11
#8575
0;
b11 C
1:
b10 =
1#
10
1.
#8580
0!
01
#8600
0#
00
0.
#8602
b100 D
1!
11
#8624
0!
01
#8625
b100 C
0:
b11 =
1#
10
1.
#8646
b101 D
1!
11
#8650
0#
00
0.
#8668
0!
01
#8675
0<
1;
b101 C
1:
b100 =
1#
10
1.
#8690
b110 D
1!
11
#8700
0#
00
0.
#8712
0!
01
#8725
b110 C
0:
b101 =
1#
10
1.
#8734
b111 D
1!
11
#8750
0#
00
0.
#8756
0!
01
#8775
0;
b111 C
1:
b110 =
1#
10
1.
#8778
b1000 D
1!
11
#8800
0!
0#
01
00
0.
#8822
b1001 D
1!
11
#8825
b1000 C
0:
b111 =
1#
10
1.
#8844
0!
01
#8850
0#
00
0.
#8866
b1010 D
1!
11
#8875
19
1<
1;
b1001 C
1:
b1000 =
1#
10
1.
#8888
0!
01
#8900
0#
00
0.
#8910
b1011 D
1!
11
#8925
b1010 C
0:
b1001 =
1#
10
1.
#8932
0!
01
#8950
0#
00
0.
#8954
b1100 D
1!
11
#8975
0;
b1011 C
1:
b1010 =
1#
10
1.
#8976
0!
01
#8998
b1101 D
1!
11
#9000
0#
00
0.
#9020
0!
01
#9025
b1100 C
0:
b1011 =
1#
10
1.
#9042
b1110 D
1!
11
#9050
0#
00
0.
#9064
0!
01
#9075
0<
1;
b1101 C
1:
b1100 =
1#
10
1.
#9086
b1111 D
1!
11
#9100
0#
00
0.
#9108
0!
01
#9125
b1110 C
0:
b1101 =
1#
10
1.
#9130
b10000 D
1!
11
#9150
0#
00
0.
#9152
0!
01
#9174
b10001 D
1!
11
#9175
0;
b1111 C
1:
b1110 =
1#
10
1.
#9196
0!
01
#9200
0#
00
0.
#9218
b10010 D
1!
11
#9225
b10000 C
0:
b1111 =
1#
10
1.
#9240
0!
01
#9250
0#
00
0.
#9262
b10011 D
1!
11
#9275
09
1<
1;
b10001 C
1:
b10000 =
1#
10
1.
#9284
0!
01
#9300
0#
00
0.
#9306
b10100 D
1!
11
#9325
b10010 C
0:
b10001 =
1#
10
1.
#9328
0!
01
#9350
b10101 D
1!
0#
11
00
0.
#9372
0!
01
#9375
0;
b10011 C
1:
b10010 =
1#
10
1.
#9394
b10110 D
1!
11
#9400
0#
00
0.
#9416
0!
01
#9425
b10100 C
0:
b10011 =
1#
10
1.
#9438
b10111 D
1!
11
#9450
0#
00
0.
#9460
0!
01
#9475
0<
1;
b10101 C
1:
b10100 =
1#
10
1.
#9482
b11000 D
1!
11
#9500
0#
00
0.
#9504
0!
01
#9525
b10110 C
0:
b100 B
b0 =
1#
10
1.
#9526
b11001 D
1!
11
#9548
0!
01
#9550
0#
00
0.
#9570
b11010 D
1!
11
#9575
0;
b10111 C
1:
b101 B
1)
1*
1#
10
1.
#9592
0!
01
#9600
0#
00
0.
#9614
b11011 D
1!
11
#9625
b11000 C
0:
b1 =
1#
10
1.
#9636
0!
01
#9650
0#
00
0.
#9658
b11100 D
1!
11
#9675
19
1<
1;
b11001 C
1:
b10 =
1#
10
1.
#9680
0!
01
#9700
0#
00
0.
#9702
b11101 D
1!
11
#9724
0!
01
#9725
b11010 C
0:
b11 =
1#
10
1.
#9746
b11110 D
1!
11
#9750
0#
00
0.
#9768
0!
01
#9775
0;
b11011 C
1:
b100 =
1#
10
1.
#9790
b11111 D
1!
11
#9800
0#
00
0.
#9812
0!
01
#9825
b11100 C
0:
b101 =
1#
10
1.
#9834
b100000 D
1!
11
#9850
0#
00
0.
#9856
0!
01
#9875
0<
1;
b11101 C
1:
b110 =
1#
10
1.
#9878
b100001 D
1!
11
#9900
0!
0#
01
00
0.
#9922
b100010 D
1!
11
#9925
b11110 C
0:
b111 =
1#
10
1.
#9944
0!
01
#9950
0#
00
0.
#9966
b100011 D
1!
11
#9975
0;
b11111 C
1:
b1000 =
1#
10
1.
#9988
0!
01
#10000
0#
00
0.
#10010
b100100 D
1!
11
#10025
b100000 C
0:
b1001 =
1#
10
1.
#10032
0!
01
#10050
0#
00
0.
#10054
b100101 D
1!
11
#10075
09
1<
1;
b100001 C
1:
b1010 =
1#
10
1.
#10076
0!
01
#10098
b100110 D
1!
11
#10100
0#
00
0.
#10120
0!
01
#10125
b100010 C
0:
b0 =
b110 B
1#
10
1.
#10142
b100111 D
1!
11
#10150
0#
00
0.
#10164
0!
01
#10175
0;
b100011 C
1:
b111 B
1+
0"
1#
10
1.
#10186
b0 D
1!
11
#10200
0#
00
0.
#10208
0!
01
#10225
b0 C
0:
1#
10
1.
#10230
1!
11
#10250
0#
00
0.
#10252
0!
01
#10274
1!
11
#10275
0<
1;
1:
1#
10
1.
#10296
0!
01
#10300
0#
00
0.
#10318
1!
11
#10325
0:
1#
10
1.
#10340
0!
01
#10350
0#
00
0.
#10362
1!
11
#10375
0;
1:
1#
10
1.
#10384
0!
01
#10400
0#
00
0.
#10406
1!
11
#10425
0:
1#
10
1.
#10428
0!
01
